popl.py
popl-0.1.4.dist-info/LICENSE
popl-0.1.4.dist-info/METADATA
popl-0.1.4.dist-info/WHEEL
popl-0.1.4.dist-info/entry_points.txt
popl-0.1.4.dist-info/top_level.txt
popl-0.1.4.dist-info/RECORD
