Metadata-Version: 2.1
Name: popl
Version: 0.1.4
Summary: A pip wrapper behaving like npm
Home-page: https://github.com/emdiet/popl
Author: emdiet
Classifier: Programming Language :: Python :: 3.7
Classifier: License :: OSI Approved :: MIT License
Classifier: Operating System :: OS Independent
Requires-Python: >=3.7
License-File: LICENSE
